{
	"institute": [
		{
								"productIdentity": "Debit",
								"code": "190525",
								"abbreviation": "ISSAUTO",
								"branch": "10985",
								"cardPackIdGenerationTemplate": "PAN723",
								"deviceIdGenerationTemplate": "PAN698",
								"embossingVendor": "V21550",
								"mastercardPrepaidIssuerBin": "526113",
								"mastercardDebitIssuerBin": "526113",
								"mastercardCreditIssuerBin": "526113",
								"visaPrepaidIssuerBin": "526113",
								"visaDebitIssuerBin": "526113",
								"visaCreditIssuerBin": "526113",
								"plasticId": "100",
								"pictureCode": "114",
								"corporateClientCode": "19052518092000001"
				},
				{
								"productIdentity": "Credit",
								"code": "190525",
								"abbreviation": "ISSAUTO",
								"branch": "10985",
								"cardPackIdGenerationTemplate": "PAN723",
								"deviceIdGenerationTemplate": "PAN698",
								"embossingVendor": "V21550",
								"mastercardPrepaidIssuerBin": "526113",
								"mastercardDebitIssuerBin": "526113",
								"mastercardCreditIssuerBin": "526113",
								"visaPrepaidIssuerBin": "526113",
								"visaDebitIssuerBin": "526113",
								"visaCreditIssuerBin": "526113",
								"plasticId": "100",
								"pictureCode": "114",
								"corporateClientCode": "19052518092000001"
				},
				{
								"productIdentity": "Prepaid",
								"code": "190525",
								"abbreviation": "ISSAUTO",
								"branch": "10985",
								"cardPackIdGenerationTemplate": "PAN723",
								"deviceIdGenerationTemplate": "PAN698",
								"embossingVendor": "V21550",
								"mastercardPrepaidIssuerBin": "526113",
								"mastercardDebitIssuerBin": "526113",
								"mastercardCreditIssuerBin": "526113",
								"visaPrepaidIssuerBin": "526113",
								"visaDebitIssuerBin": "526113",
								"visaCreditIssuerBin": "526113",
								"plasticId": "100",
								"pictureCode": "114",
								"corporateClientCode": "19052518092000001"
				},
				{
								"productIdentity": "Debit",
								"code": "666666",
								"abbreviation": "PerfCredit",
								"branch": "21659",
								"cardPackIdGenerationTemplate": "PAN756",
								"deviceIdGenerationTemplate": "PAN755",
								"embossingVendor": "V17787",
								"mastercardPrepaidIssuerBin": "VISA BIN",
								"mastercardDebitIssuerBin": "VISA BIN",
								"mastercardCreditIssuerBin": "VISA BIN",
								"visaPrepaidIssuerBin": "VISA BIN",
								"visaDebitIssuerBin": "VISA BIN",
								"visaCreditIssuerBin": "VISA BIN",
								"plasticId": "531",
								"pictureCode": "315",
								"corporateClientCode": "12121218004000045"
				},
				{
								"productIdentity": "Credit",
								"code": "666666",
								"abbreviation": "PerfCredit",
								"branch": "21659",
								"cardPackIdGenerationTemplate": "PAN756",
								"deviceIdGenerationTemplate": "PAN755",
								"embossingVendor": "V17787",
								"mastercardPrepaidIssuerBin": "VISA BIN",
								"mastercardDebitIssuerBin": "VISA BIN",
								"mastercardCreditIssuerBin": "VISA BIN",
								"visaPrepaidIssuerBin": "VISA BIN",
								"visaDebitIssuerBin": "VISA BIN",
								"visaCreditIssuerBin": "VISA BIN",
								"plasticId": "531",
								"pictureCode": "315",
								"corporateClientCode": "12121218004000045"
				},
				{
								"productIdentity": "Prepaid",
								"code": "666666",
								"abbreviation": "PerfCredit",
								"branch": "21659",
								"cardPackIdGenerationTemplate": "PAN756",
								"deviceIdGenerationTemplate": "PAN755",
								"embossingVendor": "V17787",
								"mastercardPrepaidIssuerBin": "VISA BIN",
								"mastercardDebitIssuerBin": "VISA BIN",
								"mastercardCreditIssuerBin": "VISA BIN",
								"visaPrepaidIssuerBin": "VISA BIN",
								"visaDebitIssuerBin": "VISA BIN",
								"visaCreditIssuerBin": "VISA BIN",
								"plasticId": "531",
								"pictureCode": "315",
								"corporateClientCode": "12121218004000045"
				},
				{
								"productIdentity": "Debit",
								"code": "110088",
								"abbreviation": "AUTOBNK",
								"branch": "OfficeBranch [184]",
								"cardPackIdGenerationTemplate": "Card Pack ID [PAN743]",
								"deviceIdGenerationTemplate": "CardTemplate/DeviceTemplate [PAN678]",
								"embossingVendor": "EmbossVendor [V25157]",
								"mastercardPrepaidIssuerBin": "automation prepaid card [538316]",
								"mastercardDebitIssuerBin": "automation debit card [538816]",
								"mastercardCreditIssuerBin": "537716",
								"visaPrepaidIssuerBin": "477765",
								"visaDebitIssuerBin": "487677",
								"visaCreditIssuerBin": "470110",
								"plasticId": "Plastic code [317]",
								"pictureCode": "Picture code [705]",
								"corporateClientCode": "Debit Corporate Client [11008818074000002]",
								"dedupePlanCode": "TA1025MHGA [TA1025MHGA]",
								"prepaidStatementPlan": "AUTOMATION [TA2709PNVS]",
								"statementMessagePlan": "AUTOMATION [TA8010TFFZ]",
								"marketingMessagePlan": "AUTOMATION [TA7549JQBG]",
								"documentCheckListPlan": "AUTOMATION [TA3464GGBM]",
								"mccRulePlan": "AUTOMATION [TA3242QI6]",
								"deviceJoiningAndMemberShipFeePlan": "AUTOMATION [TA8421KX]",
								"deviceEventBasedFeePlan": "AUTOMATION [TA4588OA]",
								"transactionLimitPlan": "AUTOMATION [TA9161KIEF]",
								"transactionPlan": "AUTOMATION [T1036T]",
								"creditPlan": "AUTOMATION [103]",
								"billingCycle": "AUTOMATION [141]",
								"transactionFeePlan": "Automation FIX Fee plan. [AUTOFEEP1]",
								"walletPlan": "AUTOMATION [TA8873DBAQ]"
				},
				{
								"productIdentity": "Credit",
								"code": "110088",
								"abbreviation": "AUTOBNK",
								"branch": "OfficeBranch [184]",
								"cardPackIdGenerationTemplate": "Card Pack ID [PAN743]",
								"deviceIdGenerationTemplate": "CardTemplate/DeviceTemplate [PAN678]",
								"embossingVendor": "EmbossVendor [V25157]",
								"mastercardPrepaidIssuerBin": "automation prepaid card [538316]",
								"mastercardDebitIssuerBin": "537716",
								"mastercardCreditIssuerBin": "537716",
								"visaPrepaidIssuerBin": "477765",
								"visaDebitIssuerBin": "487677",
								"visaCreditIssuerBin": "470110",
								"plasticId": "Plastic code [317]",
								"pictureCode": "Picture code [705]",
								"corporateClientCode": "Credit Corporate Client [11008818116000015]",
								"dedupePlanCode": "TA1025MHGA [TA1025MHGA]",
								"prepaidStatementPlan": "AUTOMATION [TA2709PNVS]",
								"statementMessagePlan": "AUTOMATION [TA2639BQGU]",
								"marketingMessagePlan": "AUTOMATION [TA3410JMFX]",
								"documentCheckListPlan": "AUTOMATION [TA6617GHVS]",
								"mccRulePlan": "AUTOMATION [TA7827PV6]",
								"deviceJoiningAndMemberShipFeePlan": "AUTOMATION [TA3462WP]",
								"deviceEventBasedFeePlan": "AUTOMATION [TA2430JW]",
								"transactionLimitPlan": "AUTOMATION [TA8137UMAE]",
								"transactionFeePlan": "Automation FIX Fee plan. [AUTOFEEP1]",
								"transactionPlan": "AUTOMATION [T5179K]",
								"creditPlan": "TA5339PGQX [103]",
								"billingCycle": "AUTOMATION [340]",
								"walletPlan": "AUTOMATION [TA1343CSGQ]"
				},
			 	 {
                  "productIdentity": "Prepaid",
                  "code": "110088",
                  "abbreviation": "AUTOBNK",
                  "branch": "OfficeBranch [184]",
                  "cardPackIdGenerationTemplate": "Card Pack ID [PAN743]",
                  "deviceIdGenerationTemplate": "CardTemplate/DeviceTemplate [PAN678]",
                  "embossingVendor": "EmbossVendor [V25157]",
                  "mastercardPrepaidIssuerBin": "automation prepaid card [538316]",
                  "mastercardDebitIssuerBin": "537716",
                  "mastercardCreditIssuerBin": "537716",
                  "visaPrepaidIssuerBin": "477765",
                  "visaDebitIssuerBin": "487677",
                  "visaCreditIssuerBin": "470110",
                  "plasticId": "Plastic code [317]",
                  "pictureCode": "Picture code [705]",
                  "corporateClientCode": "Prepaid Corporate Client [11008818074000001]",
                  "dedupePlanCode": "TA9889XCTG [TA9889XCTG]",
                  "prepaidStatementPlan": "AUTOMATION [TA2709PNVS]",
                  "statementMessagePlan": "AUTOMATION [TA8010TFFZ]",
                  "marketingMessagePlan": "AUTOMATION [TA7549JQBG]",
                  "documentCheckListPlan": "AUTOMATION [TA2054HCXD]",
                  "mccRulePlan": "AUTOMATION [TA6065VN9]",
                  "deviceJoiningAndMemberShipFeePlan": "AUTOMATION [TA7565TA]",
                  "deviceEventBasedFeePlan": "AUTOMATION [TA3621DE]",
                  "transactionLimitPlan": "AUTOMATION [TA7791KCVA]",
                  "transactionFeePlan": "Automation FIX Fee plan. [AUTOFEEP1]",
                  "transactionPlan": "AUTOMATION [T5756G]",
                  "creditPlan": "AUTOMATION [103]",
                  "billingCycle": "AUTOMATION [147]",
                  "walletPlan": "AUTOMATION [TA6793WTPX]"
            },

				{
								"productIdentity": "Debit",
								"code": "110000",
								"abbreviation": "CANARA",
								"branch": "100",
								"cardPackIdGenerationTemplate": "PAN004",
								"deviceIdGenerationTemplate": "PAN644",
								"embossingVendor": "CVC05",
								"mastercardPrepaidIssuerBin": "507270",
								"mastercardDebitIssuerBin": "507270",
								"mastercardCreditIssuerBin": "507270",
								"visaPrepaidIssuerBin": "507270",
								"visaDebitIssuerBin": "507270",
								"visaCreditIssuerBin": "507270",
								"plasticId": "638",
								"pictureCode": "647",
								"corporateClientCode": "11000016321000014"
				},
				{
								"productIdentity": "Credit",
								"code": "110000",
								"abbreviation": "CANARA",
								"branch": "100",
								"cardPackIdGenerationTemplate": "PAN004",
								"deviceIdGenerationTemplate": "PAN644",
								"embossingVendor": "CVC05",
								"mastercardPrepaidIssuerBin": "507270",
								"mastercardDebitIssuerBin": "507270",
								"mastercardCreditIssuerBin": "507270",
								"visaPrepaidIssuerBin": "507270",
								"visaDebitIssuerBin": "507270",
								"visaCreditIssuerBin": "507270",
								"plasticId": "638",
								"pictureCode": "647",
								"corporateClientCode": "11000016321000014"
				},
				{
								"productIdentity": "Prepaid",
								"code": "110000",
								"abbreviation": "CANARA",
								"branch": "100",
								"cardPackIdGenerationTemplate": "PAN004",
								"deviceIdGenerationTemplate": "PAN644",
								"embossingVendor": "CVC05",
								"mastercardPrepaidIssuerBin": "507270",
								"mastercardDebitIssuerBin": "507270",
								"mastercardCreditIssuerBin": "507270",
								"visaPrepaidIssuerBin": "507270",
								"visaDebitIssuerBin": "507270",
								"visaCreditIssuerBin": "507270",
								"plasticId": "638",
								"pictureCode": "647",
								"corporateClientCode": "11000016321000014"
				},
				{
								"productIdentity": "Debit",
								"code": "000035",
								"abbreviation": "LBP",
								"branch": "000003",
								"cardPackIdGenerationTemplate": "PAN766",
								"deviceIdGenerationTemplate": "PAN765",
								"embossingVendor": "V22222",
								"mastercardPrepaidIssuerBin": "554541",
								"mastercardDebitIssuerBin": "554541",
								"mastercardCreditIssuerBin": "554541",
								"visaPrepaidIssuerBin": "554541",
								"visaDebitIssuerBin": "554541",
								"visaCreditIssuerBin": "554541",
								"plasticId": "121",
								"pictureCode": "602",
								"corporateClientCode": "00003518124000003"
				},
				{
								"productIdentity": "Credit",
								"code": "000035",
								"abbreviation": "LBP",
								"branch": "000003",
								"cardPackIdGenerationTemplate": "PAN766",
								"deviceIdGenerationTemplate": "PAN765",
								"embossingVendor": "V22222",
								"mastercardPrepaidIssuerBin": "554541",
								"mastercardDebitIssuerBin": "554541",
								"mastercardCreditIssuerBin": "554541",
								"visaPrepaidIssuerBin": "554541",
								"visaDebitIssuerBin": "554541",
								"visaCreditIssuerBin": "554541",
								"plasticId": "121",
								"pictureCode": "602",
								"corporateClientCode": "00003518124000003"
				},
				{
								"productIdentity": "Prepaid",
								"code": "000035",
								"abbreviation": "LBP",
								"branch": "000003",
								"cardPackIdGenerationTemplate": "PAN766",
								"deviceIdGenerationTemplate": "PAN765",
								"embossingVendor": "V22222",
								"mastercardPrepaidIssuerBin": "554541",
								"mastercardDebitIssuerBin": "554541",
								"mastercardCreditIssuerBin": "554541",
								"visaPrepaidIssuerBin": "554541",
								"visaDebitIssuerBin": "554541",
								"visaCreditIssuerBin": "554541",
								"plasticId": "121",
								"pictureCode": "602",
								"corporateClientCode": "00003518124000003"
				},
				{
								"productIdentity": "Debit",
								"code": "270635",
								"abbreviation": "PREISSBN",
								"branch": "22179",
								"cardPackIdGenerationTemplate": "PAN768",
								"deviceIdGenerationTemplate": "PAN767",
								"embossingVendor": "AUTOB1",
								"mastercardPrepaidIssuerBin": "514786",
								"mastercardDebitIssuerBin": "532076",
								"mastercardCreditIssuerBin": "575766",
								"visaPrepaidIssuerBin": "411765",
								"visaDebitIssuerBin": "412765",
								"visaCreditIssuerBin": "413765",
								"plasticId": "712",
								"pictureCode": "316",
								"corporateClientCode": "27063518131000001"
				},
				{
								"productIdentity": "Credit",
								"code": "270635",
								"abbreviation": "PREISSBN",
								"branch": "22179",
								"cardPackIdGenerationTemplate": "PAN768",
								"deviceIdGenerationTemplate": "PAN767",
								"embossingVendor": "AUTOB1",
								"mastercardPrepaidIssuerBin": "514786",
								"mastercardDebitIssuerBin": "532076",
								"mastercardCreditIssuerBin": "575766",
								"visaPrepaidIssuerBin": "411765",
								"visaDebitIssuerBin": "412765",
								"visaCreditIssuerBin": "413765",
								"plasticId": "712",
								"pictureCode": "316",
								"corporateClientCode": "27063518131000001"
				},
				{
								"productIdentity": "Prepaid",
								"code": "270635",
								"abbreviation": "PREISSBN",
								"branch": "22179",
								"cardPackIdGenerationTemplate": "PAN768",
								"deviceIdGenerationTemplate": "PAN767",
								"embossingVendor": "AUTOB1",
								"mastercardPrepaidIssuerBin": "514786",
								"mastercardDebitIssuerBin": "532076",
								"mastercardCreditIssuerBin": "575766",
								"visaPrepaidIssuerBin": "411765",
								"visaDebitIssuerBin": "412765",
								"visaCreditIssuerBin": "413765",
								"plasticId": "712",
								"pictureCode": "316",
								"corporateClientCode": "27063518131000001"
				},
				{
								"productIdentity": "Debit",
								"code": "562220",
								"abbreviation": "LANDBANKISS",
								"branch": "81463",
								"cardPackIdGenerationTemplate": "PAN770",
								"deviceIdGenerationTemplate": "PAN769",
								"embossingVendor": "VENDOR",
								"mastercardPrepaidIssuerBin": "533214",
								"mastercardDebitIssuerBin": "578624",
								"mastercardCreditIssuerBin": "587072",
								"visaPrepaidIssuerBin": "443823",
								"visaDebitIssuerBin": "418233",
								"visaCreditIssuerBin": "470386",
								"plasticId": "567",
								"pictureCode": "779",
								"corporateClientCode": "12121218003000051"
				},
				{
								"productIdentity": "Credit",
								"code": "562220",
								"abbreviation": "LANDBANKISS",
								"branch": "81463",
								"cardPackIdGenerationTemplate": "PAN770",
								"deviceIdGenerationTemplate": "PAN769",
								"embossingVendor": "VENDOR",
								"mastercardPrepaidIssuerBin": "533214",
								"mastercardDebitIssuerBin": "578624",
								"mastercardCreditIssuerBin": "587072",
								"visaPrepaidIssuerBin": "443823",
								"visaDebitIssuerBin": "418233",
								"visaCreditIssuerBin": "470386",
								"plasticId": "567",
								"pictureCode": "779",
								"corporateClientCode": "12121218003000051"
				},
				{
								"productIdentity": "Prepaid",
								"code": "562220",
								"abbreviation": "LANDBANKISS",
								"branch": "81463",
								"cardPackIdGenerationTemplate": "PAN770",
								"deviceIdGenerationTemplate": "PAN769",
								"embossingVendor": "VENDOR",
								"mastercardPrepaidIssuerBin": "533214",
								"mastercardDebitIssuerBin": "578624",
								"mastercardCreditIssuerBin": "587072",
								"visaPrepaidIssuerBin": "443823",
								"visaDebitIssuerBin": "418233",
								"visaCreditIssuerBin": "470386",
								"plasticId": "567",
								"pictureCode": "779",
								"corporateClientCode": "12121218003000051"
				},
				{
								"productIdentity": "Debit",
								"code": "806383",
								"abbreviation": "LANDBANKMIG",
								"branch": "15407",
								"cardPackIdGenerationTemplate": "PAN772",
								"deviceIdGenerationTemplate": "PAN771",
								"embossingVendor": "VENDOR",
								"mastercardPrepaidIssuerBin": "558201",
								"mastercardDebitIssuerBin": "520575",
								"mastercardCreditIssuerBin": "561253",
								"visaPrepaidIssuerBin": "443823",
								"visaDebitIssuerBin": "418233",
								"visaCreditIssuerBin": "470386",
								"plasticId": "759",
								"pictureCode": "394",
								"corporateClientCode": "12121218003000051"
				},
				{
								"productIdentity": "Credit",
								"code": "806383",
								"abbreviation": "LANDBANKMIG",
								"branch": "15407",
								"cardPackIdGenerationTemplate": "PAN772",
								"deviceIdGenerationTemplate": "PAN771",
								"embossingVendor": "VENDOR",
								"mastercardPrepaidIssuerBin": "558201",
								"mastercardDebitIssuerBin": "520575",
								"mastercardCreditIssuerBin": "561253",
								"visaPrepaidIssuerBin": "443823",
								"visaDebitIssuerBin": "418233",
								"visaCreditIssuerBin": "470386",
								"plasticId": "759",
								"pictureCode": "394",
								"corporateClientCode": "12121218003000051"
				},
				{
								"productIdentity": "Prepaid",
								"code": "806383",
								"abbreviation": "LANDBANKMIG",
								"branch": "15407",
								"cardPackIdGenerationTemplate": "PAN772",
								"deviceIdGenerationTemplate": "PAN771",
								"embossingVendor": "VENDOR",
								"mastercardPrepaidIssuerBin": "558201",
								"mastercardDebitIssuerBin": "520575",
								"mastercardCreditIssuerBin": "561253",
								"visaPrepaidIssuerBin": "443823",
								"visaDebitIssuerBin": "418233",
								"visaCreditIssuerBin": "470386",
								"plasticId": "759",
								"pictureCode": "394",
								"corporateClientCode": "12121218003000051"
				},
				{
							   "productIdentity":"Credit",
							   "code":"303045",
							   "abbreviation":"AUTOBNG",
							   "branch":"OfficeBranch [184]",
							   "cardPackIdGenerationTemplate":"Card Pack ID Template [PAN800]",
							   "deviceIdGenerationTemplate":"Device Template [PAN799]",
							   "embossingVendor":"AUTOVENDOR [AUTO]",
							   "mastercardPrepaidIssuerBin":"MASTERCARDPREPAID [592733]",
							   "mastercardDebitIssuerBin":"MASTERCARDDEBIT [571504]",
							   "mastercardCreditIssuerBin":"MASTERCARDCREDIT [574253]",
							   "visaPrepaidIssuerBin":"VISAPREPAID [417429]",
							   "visaDebitIssuerBin":"VISADEBIT [417360]",
							   "visaCreditIssuerBin":"VISACREDIT [431112]",
							   "plasticId":"AUTOMATION PLASTIC CODE [AUT]",
							   "pictureCode":"AUTOMATION PICTURE CODE [AUT]",
							   "corporateClientCode":"Credit [30304518199000001]",
							   "dedupePlanCode":"TA4596YMGE [TA4596YMGE]",
							   "prepaidStatementPlan":"AUTOMATION [TA4048YAQU]",
							   "statementMessagePlan":"AUTOMATION [TA5447CYID]",
							   "marketingMessagePlan":"AUTOMATION [TA7617GDAV]",
							   "documentCheckListPlan":"AUTOMATION [TA4886UCOI]",
							   "mccRulePlan":"AUTOMATION [TA8071XO6]",
							   "deviceJoiningAndMemberShipFeePlan":"AUTOMATION [TA2699UL]",
							   "deviceEventBasedFeePlan":"AUTOMATION [TA3264SL]",
							   "transactionLimitPlan":"AUTOMATION [TA9706ODEV]",
							   "transactionPlan":"AUTOMATION [T7185S]",
							   "creditPlan":"Automation [100]",
							   "transactionFeePlan": "Automation FIX Fee plan. [AUTOFEEP1]",
							   "billingCycle":"Automation Billing [100]",
							   "walletPlan":"AUTOMATION [TA4946EBFC]"
  				 },
  				 {
							   "productIdentity":"Prepaid",
							   "code":"111777",
							   "abbreviation":"LANKA",
							   "branch":"OfficeBranch [184]",
							   "cardPackIdGenerationTemplate":"Card Pack ID Template [PAN811]",
							   "deviceIdGenerationTemplate":"Device Template [PAN809]",
							   "embossingVendor":"AUTOVENDOR [AUTO]",
							   "mastercardPrepaidIssuerBin":"Prepaid SMS MasterCard [520495]",
							   "mastercardDebitIssuerBin":"MASTERCARDDEBIT [571504]",
							   "mastercardCreditIssuerBin":"MASTERCARDCREDIT [574253]",
							   "visaPrepaidIssuerBin":"VISAPREPAID [417429]",
							   "visaDebitIssuerBin":"VISADEBIT [417360]",
							   "visaCreditIssuerBin":"VISACREDIT [431112]",
							   "plasticId":"Plastic code [266]",
							   "pictureCode":"Picture code [827]",
							   "corporateClientCode":"MasterCard [11177716335000002]",
							   "dedupePlanCode":"AMIT2018 [AMIT2018]",
							   "prepaidStatementPlan":"AUTOMATION [TA8875TKOG]",
							   "statementMessagePlan":"AUTOMATION [TA8779MXGU]",
							   "marketingMessagePlan":"AUTOMATION [TA6030TTOJ]",
							   "documentCheckListPlan":"AUTOMATION [TA2964SGFH]",
							   "mccRulePlan":"AUTOMATION [TA9181XR0]",
							   "deviceJoiningAndMemberShipFeePlan":"AUTOMATION [TA8300LD]",
							   "deviceEventBasedFeePlan":"AUTOMATION [TA2723HM]",
							   "transactionLimitPlan":"LOAD111 [LOAD111]",
							   "transactionPlan":"AUTOMATION [T66888]",
							   "creditPlan":"Credit Plan [233]",
							   "billingCycle":"Credit Bill [012]",
							   "transactionFeePlan": "Automation FIX Fee plan. [AUTOFEEP1]",
							   "walletPlan":"MultiCurrency INR [WP03]"
  				 }
]
}